PyFGH/GUI.py
PyFGH/GUItoCalc.py
PyFGH/Gmatrix.py
PyFGH/Tmatrix.py
PyFGH/Vmatrix.py
PyFGH/__init__.py
PyFGH/jnw-test10.py
PyFGH/jnw-test13.py
PyFGH/jnw-test5.py
PyFGH/jnw-test8.py
PyFGH/jnw-test9.py
PyFGH/jnwtest11.py
PyFGH/main.py
PyFGH/molecule_gui.py
PyFGH/util/DataObject.py
PyFGH/util/__init__.py
PyFGH/util/model_objects.py
PyFGH/util/pyfghutil.py
PyFGH-0.3.7.dist-info/METADATA
PyFGH-0.3.7.dist-info/WHEEL
PyFGH-0.3.7.dist-info/top_level.txt
PyFGH-0.3.7.dist-info/RECORD
