Metadata-Version: 2.1
Name: PyFGH
Version: 0.3.7
Summary: PyFGH library
Author: Josiah Randleman, Nelson Maxey, Tyler Law, Dr. Jeffrey Woodford
License: MIT
Classifier: Intended Audience :: Developers
Classifier: License :: OSI Approved :: MIT License
Classifier: Programming Language :: Python
Classifier: Programming Language :: Python :: 3
Classifier: Programming Language :: Python :: 3.6
Classifier: Programming Language :: Python :: 3.7
Classifier: Programming Language :: Python :: 3.8
Classifier: Programming Language :: Python :: 3.9
Classifier: Operating System :: OS Independent
